[
    {
        "name": "Разработчик Frontend (React)",
        "salary": 250000,
        "description": "Разработка проектов с использованием React. Доработка готовых проектов (исправление багов, расширение функциональности). Миграция функционала из старой системы в новую, при...",
        "url": "https://hh.ru/vacancy/106694311"
    },
    {
        "name": "Стажёр-разработчик",
        "salary": 25000,
        "description": "Разработка backend и frontend частей web, десктопных и мобильных приложений. Анализ требований, проектирование архитектуры, тестирование. Поддержка production- и <highlighttext>development</highlighttext> инфраструктуры. ",
        "url": "https://hh.ru/vacancy/105990880"
    }
]